django_aws_storage_28814/__init__.py
django_aws_storage_28814-0.1.0.dist-info/METADATA
django_aws_storage_28814-0.1.0.dist-info/WHEEL
django_aws_storage_28814-0.1.0.dist-info/top_level.txt
django_aws_storage_28814-0.1.0.dist-info/RECORD
